cabarchive/__init__.py
cabarchive/__init__.pyi
cabarchive/archive.py
cabarchive/archive.pyi
cabarchive/cli.py
cabarchive/errors.py
cabarchive/errors.pyi
cabarchive/file.py
cabarchive/file.pyi
cabarchive/parser.py
cabarchive/parser.pyi
cabarchive/py.typed
cabarchive/test_misc.py
cabarchive/utils.py
cabarchive/utils.pyi
cabarchive/writer.py
cabarchive/writer.pyi
cabarchive-0.2.3.dist-info/LICENSE
cabarchive-0.2.3.dist-info/METADATA
cabarchive-0.2.3.dist-info/WHEEL
cabarchive-0.2.3.dist-info/top_level.txt
cabarchive-0.2.3.dist-info/RECORD
