Metadata-Version: 2.1
Name: cabarchive
Version: 0.2.3
Summary: A pure-python library for creating and extracting cab files
Home-page: https://github.com/hughsie/python-cabarchive
Author: Richard Hughes
Author-email: richard@hughsie.com
License: LGPL-2.1-or-later
Keywords: cabextract,cab,archive,extract
Platform: UNKNOWN
Classifier: Development Status :: 4 - Beta
Classifier: Intended Audience :: Developers
Classifier: License :: OSI Approved :: GNU Lesser General Public License v2 or later (LGPLv2+)
Classifier: Programming Language :: Python
Classifier: Programming Language :: Python :: 2.7
Classifier: Topic :: Utilities
Classifier: Topic :: System :: Archiving
